limecore/core/di/__init__.py
limecore/core/di/application.py
limecore_core_di-0.2.2.dist-info/LICENSE.txt
limecore_core_di-0.2.2.dist-info/METADATA
limecore_core_di-0.2.2.dist-info/WHEEL
limecore_core_di-0.2.2.dist-info/top_level.txt
limecore_core_di-0.2.2.dist-info/RECORD
